smt_planning/__init__.py
smt_planning/dicts/CapabilityDictionary.py
smt_planning/dicts/PropertyDictionary.py
smt_planning/dicts/ResourceDictionary.py
smt_planning/dicts/name_util.py
smt_planning/ontology_handling/capability_and_property_query.py
smt_planning/ontology_handling/capability_constraints_query.py
smt_planning/ontology_handling/init_query.py
smt_planning/ontology_handling/query_handlers.py
smt_planning/ontology_handling/related_inits.py
smt_planning/openmath/__init__.py
smt_planning/openmath/application.py
smt_planning/openmath/math_symbol_information.py
smt_planning/openmath/operator_dictionary.py
smt_planning/openmath/parse_openmath.py
smt_planning/planner_cli.py
smt_planning/planner_rest.py
smt_planning/planning_result.py
smt_planning/smt/StateHandler.py
smt_planning/smt/__init__.py
smt_planning/smt/bind_floating_vars.py
smt_planning/smt/bool_variable_support.py
smt_planning/smt/capability_constraints.py
smt_planning/smt/capability_effects.py
smt_planning/smt/capability_links.py
smt_planning/smt/capability_mutexes.py
smt_planning/smt/capability_preconditions.py
smt_planning/smt/cask_to_smt.py
smt_planning/smt/constraints_bools.py
smt_planning/smt/constraints_real_variables.py
smt_planning/smt/fix_constants.py
smt_planning/smt/goal.py
smt_planning/smt/init.py
smt_planning/smt/property_links.py
smt_planning/smt/real_variable_contin_change.py
smt_planning/smt/variable_declaration.py
smt_planning/types/InstanceDescription.py
smt_planning/types/Property.py
smt_planning/types/PropertyOccurrence.py
caskade_planner-1.0.3.dist-info/LICENSE
caskade_planner-1.0.3.dist-info/METADATA
caskade_planner-1.0.3.dist-info/WHEEL
caskade_planner-1.0.3.dist-info/entry_points.txt
caskade_planner-1.0.3.dist-info/RECORD
