Metadata-Version: 2.3
Name: caskade-planner
Version: 1.0.3
Summary: An automated process planning approach based on a capability ontology and Satisfiability Modulo Theories
Author: Luis Miguel Vieira da Silva
Author-email: miguel.vieira@hsu-hh.de
Requires-Python: >=3.11,<4.0
Classifier: Programming Language :: Python :: 3
Classifier: Programming Language :: Python :: 3.11
Classifier: Programming Language :: Python :: 3.12
Classifier: Programming Language :: Python :: 3.13
Requires-Dist: flask (>=3.0.0,<4.0.0)
Requires-Dist: flask-cors (>=4.0.0,<5.0.0)
Requires-Dist: rdflib (>=7.0.0,<8.0.0)
Requires-Dist: requests (>=2.31.0,<3.0.0)
Requires-Dist: setuptools (>=80.9.0,<81.0.0)
Requires-Dist: typer (>=0.9.0,<0.10.0)
Requires-Dist: z3-solver (>=4.12.2.0,<5.0.0.0)
